sayql/__init__.py
sayql/prompt.py
sayql/sayql.py
sayql-0.1.1.dist-info/LICENSE
sayql-0.1.1.dist-info/WHEEL
sayql-0.1.1.dist-info/METADATA
sayql-0.1.1.dist-info/RECORD
