Metadata-Version: 2.1
Name: sayql
Version: 0.1.1
Summary: Talk to your data
License: MIT
Author: Ryan
Author-email: ryan.sudhakaran@gmail.com
Requires-Python: >=3.10,<4.0
Classifier: License :: OSI Approved :: MIT License
Classifier: Programming Language :: Python :: 3
Classifier: Programming Language :: Python :: 3.10
Requires-Dist: duckdb (>=0.8.0,<0.9.0)
Requires-Dist: langchain (>=0.0.179,<0.0.180)
Requires-Dist: openai (>=0.27.7,<0.28.0)
Requires-Dist: pandas (>=2.0.1,<3.0.0)
